{
    "bgcolors": [
        "d5d7e1",
        "e1d7d5"
    ],
    "partcolors": [
        "",
        "CCD3E0",
        "E0E0E0",
        "FCC02E",
        "0F0F0F",
        "BAD1CB",
        "F4BAAC",
        "C1D3E5",
        "DE9400",
        "F8E100",
        "C7B300",
        "5E6E80",
        "718499",
        "CCCA66",
        "A6A453",
        "2B2B2B",
        "4D4D4D",
        "262626",
        "1A1A1A",
        "F3EBEE",
        "D2212B",
        "E33A3B",
        "17110C",
        "664D37",
        "594330",
        "876549",
        "7B8FA6",
        "8EA5BF",
        "343434",
        "636363",
        "4A4A4A",
        "0D1114",
        "CCCCCC",
        "E5E5E5",
        "F2F2F2",
        "C7C7C7",
        "5C3C0D",
        "151515",
        "302725",
        "C69455",
        "AD814B",
        "A56F3B",
        "FFFFFF",
        "D9D9D9",
        "452C09",
        "66410D",
        "4372E0",
        "283C2D",
        "982729",
        "EBDFCC",
        "F52A2A",
        "D92525",
        "CC2323",
        "E52727",
        "CCC2B1",
        "5752FF",
        "FF3636",
        "1F1F1F",
        "404040",
        "000000",
        "0D0D0D",
        "080808",
        "121212",
        "B5B5B5",
        "D4D2CF",
        "CC2929",
        "1A0402",
        "2E1412",
        "2F0704",
        "BFBFBF",
        "242424",
        "666666",
        "B38807",
        "CF9D08",
        "616161",
        "6E6E6E",
        "171717",
        "B3B3B3",
        "C9C9C9",
        "4D492C",
        "787346",
        "333333",
        "ABBCCC",
        "E3EBFA",
        "B38565",
        "9F6E4C",
        "9EA3AD",
        "B38D6F",
        "A37855",
        "CFA380",
        "BD8B62",
        "465459",
        "5B6C73",
        "2E2319",
        "C2B9A9",
        "9E978A",
        "382A1E",
        "4F3C2B",
        "856448",
        "474747",
        "D1D1D1",
        "B0B0B0",
        "211912",
        "0D1314",
        "AE6C37",
        "3D0C0C",
        "0F0D0D",
        "9E7755",
        "FAC52C",
        "CCA225",
        "260603",
        "E0CCCC",
        "9A5682",
        "C872A6",
        "ADA8AA",
        "C7C1C3",
        "D9D2D4",
        "E5DFE1",
        "222421",
        "F22929",
        "A67B47",
        "B5874E",
        "8C5E32",
        "B32424",
        "7E5A3F",
        "8E6546"
    ],
    "parts": [
        [
            {
                "name": "1-silver-ring",
                "gender": "men",
                "category": "rings",
                "data": "0x00222723260101"
            }
        ],
        [
            {
                "name": "3-platinum-ring",
                "gender": "men",
                "category": "rings",
                "data": "0x00222723260102"
            }
        ],
        [
            {
                "name": "0-gold-ring",
                "gender": "men",
                "category": "rings",
                "data": "0x00222723260103"
            }
        ],
        [
            {
                "name": "6-thumb-ring",
                "gender": "men",
                "category": "rings",
                "data": "0x00202621250104"
            }
        ],
        [
            {
                "name": "4-titanium-ring",
                "gender": "men",
                "category": "rings",
                "data": "0x00222723260105"
            }
        ],
        [
            {
                "name": "5-pinky-ring",
                "gender": "men",
                "category": "rings",
                "data": "0x00222723260106"
            }
        ],
        [
            {
                "name": "2-diamond-ring",
                "gender": "men",
                "category": "rings",
                "data": "0x00222723260107"
            }
        ],
        [
            {
                "name": "0-Bronze-Chain-w",
                "gender": "girls",
                "category": "neck",
                "data": "0x001424171f010804000100010802000108020002080100"
            }
        ],
        [
            {
                "name": "1-Silver-Chain-w",
                "gender": "girls",
                "category": "neck",
                "data": "0x001424171f010104000100010102000101020002010100"
            }
        ],
        [
            {
                "name": "2-Gold-Chain-w",
                "gender": "girls",
                "category": "neck",
                "data": "0x001424171f010304000100010302000103020002030100"
            }
        ],
        [
            {
                "name": "0-Rubber-Gloves-W",
                "gender": "girls",
                "category": "hands",
                "data": "0x001d26231a010001090900010901000109090001090100010909000109010a01090800010a0109010a010909000109010a0900010a0100"
            }
        ],
        [
            {
                "name": "5-Nitrile-Gloves-W",
                "gender": "girls",
                "category": "hands",
                "data": "0x002026231a010b010c0800010b010c010b010c0900010c010b0900010b0100"
            }
        ],
        [
            {
                "name": "11-Kevlar-Gloves-W",
                "gender": "girls",
                "category": "hands",
                "data": "0x001f26231a0100010d0900010d010e010d0800010e010d010e010d0900010d010e0900010e0100"
            }
        ],
        [
            {
                "name": "3-MMA-Wraps-W",
                "gender": "girls",
                "category": "hands",
                "data": "0x002026231a020f0800020f010f01100800010f01100110010f08000110010f"
            }
        ],
        [
            {
                "name": "8-Leather-Gloves-W",
                "gender": "girls",
                "category": "hands",
                "data": "0x001e26231a01000111090001120100011109000112011201110800021201120111090001120112090001120100"
            }
        ],
        [
            {
                "name": "2-Boxing-Gloves-W",
                "gender": "girls",
                "category": "hands",
                "data": "0x001f27231a010001130900011301000114011501140700011401150114020f011507000115020f0114011501140700011401150114"
            }
        ],
        [
            {
                "name": "6-Studded-Leather-Gloves-W",
                "gender": "girls",
                "category": "hands",
                "data": "0x001e26231a010001160900011601000116090001160116010108000116010101010116090001160116090001160101"
            }
        ],
        [
            {
                "name": "1-Baseball-Gloves-W",
                "gender": "girls",
                "category": "hands",
                "data": "0x001f28252301000117011801170100011701180117011801170117011902170118011701190117011801170200021701180200011701180100"
            }
        ],
        [
            {
                "name": "12-Surgical-Gloves-W",
                "gender": "girls",
                "category": "hands",
                "data": "0x002026231a011a011b0800011a011b011a011b0900011b011a0900011a0100"
            }
        ],
        [
            {
                "name": "10-Black-Gloves-W",
                "gender": "girls",
                "category": "hands",
                "data": "0x002026231a011201110800021201120111090001120112090001120100"
            }
        ],
        [
            {
                "name": "4-Winter-Gloves-W",
                "gender": "girls",
                "category": "hands",
                "data": "0x002026231a0116011c08000116011c0116011c0900011c011d0900011d0100"
            }
        ],
        [
            {
                "name": "7-Combat-Gloves-W",
                "gender": "girls",
                "category": "hands",
                "data": "0x001f26231a0100011609000116011e011d0800011e011d011e011d0900011d021e0800021e"
            }
        ],
        [
            {
                "name": "13-Fingerless-Gloves-W",
                "gender": "girls",
                "category": "hands",
                "data": "0x002026221a011201110900011f01120a00011f"
            }
        ],
        [
            {
                "name": "9-White-Gloves-W",
                "gender": "girls",
                "category": "hands",
                "data": "0x002026231a0120012108000120012101200121090001210120090001200100"
            }
        ],
        [
            {
                "name": "10-Converse-All-Stars",
                "gender": "men",
                "category": "shoes",
                "data": "0x003327371c011f011c0400011f011c03000122011c0400011f0122011c0200011f0123011c0300011f031c012301210222030001210422"
            }
        ],
        [
            {
                "name": "9-Dress-Shoes",
                "gender": "men",
                "category": "shoes",
                "data": "0x003327361c01000124050001250124020001250211030004250100042502000525"
            }
        ],
        [
            {
                "name": "5-Timberlands",
                "gender": "men",
                "category": "shoes",
                "data": "0x003227371b01260200012603000326020001000226040002260127020001000228040001290327010001280227012803000527042903000529"
            }
        ],
        [
            {
                "name": "1-White-Forces",
                "gender": "men",
                "category": "shoes",
                "data": "0x003327371c01210100012a0500012a02000120012101200300022a0120012a01000121022a03000320022a012b02220300012b0422"
            }
        ],
        [
            {
                "name": "15-Open-Toe-Sandals",
                "gender": "men",
                "category": "shoes",
                "data": "0x003427371b0100012c01240400012c022d02000124020001240600012d0100042c0300052c"
            }
        ],
        [
            {
                "name": "14-Socks",
                "gender": "men",
                "category": "shoes",
                "data": "0x003026361c022e0400022e02000120012104000120012102000120012104000120012102000120012104000120012102000121012004000120022101000120012101200300012e0321"
            }
        ],
        [
            {
                "name": "12-Gucci-Slides",
                "gender": "men",
                "category": "shoes",
                "data": "0x003427371c0100012f0500012f0130012f0100012f0100012f0400012f0130012f010001200221030001200421"
            }
        ],
        [
            {
                "name": "7-Flip-Flops",
                "gender": "men",
                "category": "shoes",
                "data": "0x003527371c01000121070001210100032003000520"
            }
        ],
        [
            {
                "name": "2-Air-Jordan-1-Chicagos",
                "gender": "men",
                "category": "shoes",
                "data": "0x003227371c01000131050001320131020001330131013303000133023202000125013401250300013301310125013201000135023203000325023201360231030001360431"
            }
        ],
        [
            {
                "name": "6-Reebok-Classics",
                "gender": "men",
                "category": "shoes",
                "data": "0x003327371c0100012b0600012a02000137012201380300012a01370138012a01000122012a01220300052a032b0300052b"
            }
        ],
        [
            {
                "name": "0-Black-Air-Force-1s",
                "gender": "men",
                "category": "shoes",
                "data": "0x003327371c013901000139050001390200013a013b013a0300013c0139013a0139010003390300033a0239013d023e0300013d043e"
            }
        ],
        [
            {
                "name": "4-Air-Max-95",
                "gender": "men",
                "category": "shoes",
                "data": "0x003327371c0121012001210300012a013f012a0200013f0122013f0300023f022a0100032a03000121042a0120022b03000120042b"
            }
        ],
        [
            {
                "name": "8-Nike-Cortez",
                "gender": "men",
                "category": "shoes",
                "data": "0x003327371c014007000122020001410121040001210122014101220100014102220300034102220120022b03000120042b"
            }
        ],
        [
            {
                "name": "13-Alligator-Dress-Shoes",
                "gender": "men",
                "category": "shoes",
                "data": "0x003327361c0100014206000143020001420244030001420144014201440100044202000542"
            }
        ],
        [
            {
                "name": "11-White-Slippers",
                "gender": "men",
                "category": "shoes",
                "data": "0x003527371c01210222060002220145022b0300052b"
            }
        ],
        [
            {
                "name": "3-Gucci-Tennis-84",
                "gender": "men",
                "category": "shoes",
                "data": "0x003327371c0100012b0600012202000130012f013003000122012f0130012f0100012f0122012f03000122012f0130012f0122032b0300052b"
            }
        ],
        [
            {
                "name": "0-Pocket-Knife",
                "gender": "men",
                "category": "weapons",
                "data": "0x00211b27160400013b0300013b01000200015b013b01000100025b0200025c0300015b0400"
            }
        ],
        [
            {
                "name": "8-Tire-Iron",
                "gender": "men",
                "category": "weapons",
                "data": "0x00211b2d170300015d04000300015d0300015d0300015d0300015d0300015d0300015d0300015d0300015d0300015d035d0100"
            }
        ],
        [
            {
                "name": "11-Razor-Blade",
                "gender": "men",
                "category": "weapons",
                "data": "0x00211b27190100011802000100015e015f015e015f015e015f015e"
            }
        ],
        [
            {
                "name": "5-AK47",
                "gender": "men",
                "category": "weapons",
                "data": "0x001b1e30180100016002610200010001600261020001000160016103000100016001610300010001600400011f01120400011f011201610300011f01120400011f01120400011f02120300011f03120200011f0112010002120100011f0161020002120160016103000112016001610400016001610400011f01120400010001120400010001120400011f01120400010001120400"
            }
        ],
        [
            {
                "name": "6-Shovel",
                "gender": "men",
                "category": "weapons",
                "data": "0x00211d3318010002600200010001600100016001000200016002000200016002000200016202000200016202000200016202000200016202000200016202000200016202000200016302000200016302000200016302000563056305630563010003630100"
            }
        ],
        [
            {
                "name": "1-Chain",
                "gender": "men",
                "category": "weapons",
                "data": "0x00211b2e19010001640165010001650100026501000164016501640165010002650100016401650164016501000165016401000164"
            }
        ],
        [
            {
                "name": "3-Crowbar",
                "gender": "men",
                "category": "weapons",
                "data": "0x00211b291802000116030002000116020001160200011602000116011601000116010001160100"
            }
        ],
        [
            {
                "name": "9-Police-Baton",
                "gender": "men",
                "category": "weapons",
                "data": "0x00211b2c1802000166030002000166036602000166020001660200016602000166020001660200016602000166"
            }
        ],
        [
            {
                "name": "12-Chain",
                "gender": "men",
                "category": "weapons",
                "data": "0x00211b2e19010001640165010001650100026501000164016501640165010002650100016401650164016501000165016401000164"
            }
        ],
        [
            {
                "name": "2-Knife",
                "gender": "men",
                "category": "weapons",
                "data": "0x001a21221a0600015b0500025b0400035c0300035c01000200035b02000167035b030001000167015b04000168010001670400"
            }
        ],
        [
            {
                "name": "10-Pepper-Spray",
                "gender": "men",
                "category": "weapons",
                "data": "0x00211c26160200021e0100011e02000169036a02000102030001000102010001020200010201000102010001020100"
            }
        ],
        [
            {
                "name": "17-Uzi",
                "gender": "men",
                "category": "weapons",
                "data": "0x001f1e27160100021c05000100011c011605000100011c0216010003160100011c0116041c01000100011c0116011c04000100011c01160500011c02160500010001160600"
            }
        ],
        [
            {
                "name": "14-Brass-Knuckles",
                "gender": "men",
                "category": "weapons",
                "data": "0x00201d24190200013b01000100013b0100013b013b0100013b01000100013b0200"
            }
        ],
        [
            {
                "name": "4-Handgun",
                "gender": "men",
                "category": "weapons",
                "data": "0x00211b28180100023e0151013e01000251010001510200015102000151020001510200"
            }
        ],
        [
            {
                "name": "7-Baseball-Bat",
                "gender": "men",
                "category": "weapons",
                "data": "0x00211b3319010001160200010001160100011601000116010001160100016b0162016b0162016b0162016b0162016b0162016b0162016b0162016b0162016b0162016b0162016b0262"
            }
        ],
        [
            {
                "name": "15-Shotgun",
                "gender": "men",
                "category": "weapons",
                "data": "0x00211c30180100013b0100013b033b0100023b0200013b011c0200013b011c0200013b011c0200013b011c0200013b011c0200013b011c0200013b011c0200013b011c0200013b011c0200013b011c0200013b011c0200013b0300"
            }
        ],
        [
            {
                "name": "13-Taser",
                "gender": "men",
                "category": "weapons",
                "data": "0x00201c26180100013b0100013b033b0100023b0200013b011c0200013b011c0200016c016d0200"
            }
        ],
        [
            {
                "name": "16-Glock",
                "gender": "men",
                "category": "weapons",
                "data": "0x00201c2518010001160200021601000116010002160100010001160200010001160200"
            }
        ],
        [
            {
                "name": "7-Suspenders-w",
                "gender": "girls",
                "category": "waist",
                "data": "0x001424201e014604000146014604000146014604000146014604000146014704000147014604000146014604000146014604000146014604000146014604000146014604000146014704000147"
            }
        ],
        [
            {
                "name": "4-Concealed-Holster-w",
                "gender": "girls",
                "category": "waist",
                "data": "0x001f24221c0100013b011f013b031f013b023b011f013b031f013b013b0700"
            }
        ],
        [
            {
                "name": "0-Gucci-Belt-w",
                "gender": "girls",
                "category": "waist",
                "data": "0x001d24211e030001480200020001480300013b011f0148011f0149011f030001490200"
            }
        ],
        [
            {
                "name": "14-Sash-w",
                "gender": "girls",
                "category": "waist",
                "data": "0x001325241c0700013b01000700014801490700013b01000700014801490600013b020006000148014901000500013b030005000148014902000400013b040004000148014903000300013b050003000148014904000200013b060002000148014905000100013b0700014801490700013b0800"
            }
        ],
        [
            {
                "name": "10-Pistol-Holster-w",
                "gender": "girls",
                "category": "waist",
                "data": "0x002024231c0100033b014a014b011f013b013b0700013b0700"
            }
        ],
        [
            {
                "name": "12-Knife-Holster-w",
                "gender": "girls",
                "category": "waist",
                "data": "0x002620291d014c02000100024c014c0200"
            }
        ],
        [
            {
                "name": "9-Metal-Belt-w",
                "gender": "girls",
                "category": "waist",
                "data": "0x001f24201e014d014e014a014b014d014e"
            }
        ],
        [
            {
                "name": "8-Military-Belt-w",
                "gender": "girls",
                "category": "waist",
                "data": "0x001f24201e014f0150014f0146014f0150"
            }
        ],
        [
            {
                "name": "3-Taser-Holster-w",
                "gender": "girls",
                "category": "waist",
                "data": "0x001f25221c0100013b011f0151031f0151011f023b011f013b031f013b011f013b0200013b0300013b0100"
            }
        ],
        [
            {
                "name": "5-Diamond-Belt-w",
                "gender": "girls",
                "category": "waist",
                "data": "0x001f24201e023b01520107023b"
            }
        ],
        [
            {
                "name": "15-Fanny-Pack-w",
                "gender": "girls",
                "category": "waist",
                "data": "0x002024231d023b011f0112031103000112031103000412"
            }
        ],
        [
            {
                "name": "2-Studded-Belt-w",
                "gender": "girls",
                "category": "waist",
                "data": "0x001f24201e0153013b0101013b0153013b"
            }
        ],
        [
            {
                "name": "1-Versace-Belt-w",
                "gender": "girls",
                "category": "waist",
                "data": "0x001e24211e02000148010001490100013b011f0148011f0149011f030001490200"
            }
        ],
        [
            {
                "name": "11-SMG-Holster-w",
                "gender": "girls",
                "category": "waist",
                "data": "0x002024261c0100023b021f014a021f0100013b0600023b06000100013b06000100023b011f04000100013b0600"
            }
        ],
        [
            {
                "name": "6-D-Ring-Belt-w",
                "gender": "girls",
                "category": "waist",
                "data": "0x001f24231e014c01460147014c02460300014c02000300014c02000300014c0200"
            }
        ],
        [
            {
                "name": "13-Laces-w",
                "gender": "girls",
                "category": "waist",
                "data": "0x001f24241e0154015501540155015401550200015501000155010002000154010001540100020001550300020001540300"
            }
        ],
        [
            {
                "name": "2-Studded-Belt",
                "gender": "men",
                "category": "waist",
                "data": "0x001f25201c0156013b0153013b0101013b0153013b0101"
            }
        ],
        [
            {
                "name": "7-Suspenders",
                "gender": "men",
                "category": "waist",
                "data": "0x001124201e014604000146014604000146014604000146014604000146014704000147014604000146014604000146014604000146014604000146014604000146014604000146014604000146014604000146014604000146014704000147"
            }
        ],
        [
            {
                "name": "1-Versace-Belt",
                "gender": "men",
                "category": "waist",
                "data": "0x001e25211c04000148010001490200023b021f0148011f0149021f050001490300"
            }
        ],
        [
            {
                "name": "0-Gucci-Belt",
                "gender": "men",
                "category": "waist",
                "data": "0x001d25211c050001480300040001480400023b021f0148011f0149021f050001490300"
            }
        ],
        [
            {
                "name": "10-Pistol-Holster",
                "gender": "men",
                "category": "waist",
                "data": "0x001f25221b0100043b014a014b011f023b013b0900013b0900"
            }
        ],
        [
            {
                "name": "3-Taser-Holster",
                "gender": "men",
                "category": "waist",
                "data": "0x001e25211b0100023b011f0151031f0151011f033b011f013b031f013b011f013b0300013b0300013b0100"
            }
        ],
        [
            {
                "name": "14-Sash",
                "gender": "men",
                "category": "waist",
                "data": "0x001125221c0700013b01000700014801490700013b01000700014801490600013b020006000148014901000500013b030005000148014902000400013b040004000148014903000300013b050003000148014904000200013b060002000148014905000100013b0700014801490700013b0800"
            }
        ],
        [
            {
                "name": "9-Metal-Belt",
                "gender": "men",
                "category": "waist",
                "data": "0x001f25201c014d014e014d014e014a014b014d014e014d"
            }
        ],
        [
            {
                "name": "4-Concealed-Holster",
                "gender": "men",
                "category": "waist",
                "data": "0x001e25211b0100023b011f013b031f013b011f033b011f013b031f013b011f013b0900"
            }
        ],
        [
            {
                "name": "15-Fanny-Pack",
                "gender": "men",
                "category": "waist",
                "data": "0x001f25221c023b021f01120311011f0400011203110100040004120100"
            }
        ],
        [
            {
                "name": "12-Knife-Holster",
                "gender": "men",
                "category": "waist",
                "data": "0x00271f2a1b014603000100024c014601460300"
            }
        ],
        [
            {
                "name": "13-Laces",
                "gender": "men",
                "category": "waist",
                "data": "0x001f25241c015701580159015a0159015a0159015a01590400015a0100015a0200040001590100015902000400015a0400040001590400"
            }
        ],
        [
            {
                "name": "11-SMG-Holster",
                "gender": "men",
                "category": "waist",
                "data": "0x001f25251b0100023b031f024a021f0100013b0800023b08000100013b08000100023b011f06000100013b0800"
            }
        ],
        [
            {
                "name": "6-D-Ring-Belt",
                "gender": "men",
                "category": "waist",
                "data": "0x001f25231c024c02460147014c03460500014c03000500014c03000500014c0300"
            }
        ],
        [
            {
                "name": "8-Military-Belt",
                "gender": "men",
                "category": "waist",
                "data": "0x001f25201c024f0250014f0146014f0250"
            }
        ],
        [
            {
                "name": "1-silver-ring",
                "gender": "girls",
                "category": "rings",
                "data": "0x00222623250101"
            }
        ],
        [
            {
                "name": "3-platinum-ring",
                "gender": "girls",
                "category": "rings",
                "data": "0x00222623250102"
            }
        ],
        [
            {
                "name": "0-gold-ring",
                "gender": "girls",
                "category": "rings",
                "data": "0x00222623250103"
            }
        ],
        [
            {
                "name": "6-thumb-ring",
                "gender": "girls",
                "category": "rings",
                "data": "0x00202521240104"
            }
        ],
        [
            {
                "name": "4-titanium-ring",
                "gender": "girls",
                "category": "rings",
                "data": "0x00222623250105"
            }
        ],
        [
            {
                "name": "5-pinky-ring",
                "gender": "girls",
                "category": "rings",
                "data": "0x00222623250106"
            }
        ],
        [
            {
                "name": "2-diamond-ring",
                "gender": "girls",
                "category": "rings",
                "data": "0x00222623250107"
            }
        ],
        [
            {
                "name": "1_white-forces-w",
                "gender": "girls",
                "category": "shoes",
                "data": "0x003326371d012a0500012a020001200122030001220120012a01000120022102000220022a0145022b0200012b0322"
            }
        ],
        [
            {
                "name": "13_alligator-dress-shoes-w",
                "gender": "girls",
                "category": "shoes",
                "data": "0x003426371d01000142040001440200016e0144016e02000144014201440100034202000142014401420144"
            }
        ],
        [
            {
                "name": "3_gucci-tennis-84-w",
                "gender": "girls",
                "category": "shoes",
                "data": "0x003326371d012a050001220200012f013003000122012f01300100012f022202000122012f01300122032b0200042b"
            }
        ],
        [
            {
                "name": "14_socks-w",
                "gender": "girls",
                "category": "shoes",
                "data": "0x003125361e016f0300016f020001700300017102000171030001700200017001710200017101700100017102700100016f01710170"
            }
        ],
        [
            {
                "name": "10_converse-all-stars-w",
                "gender": "girls",
                "category": "shoes",
                "data": "0x003326371e011f0300011f03000113011f02000113011c0200011f02720100011f021c017301740213010001750313"
            }
        ],
        [
            {
                "name": "0_black-air-force-1s-w",
                "gender": "girls",
                "category": "shoes",
                "data": "0x003326371d0139050001390200013a013c0300013c013a01390100017602390200023a0239013d023e0200013d033e"
            }
        ],
        [
            {
                "name": "12_gucci-slides-w",
                "gender": "girls",
                "category": "shoes",
                "data": "0x003426371d010001300400012f0200012f0100012f0300012f01300100012002210200042b"
            }
        ],
        [
            {
                "name": "4_airmax-95-w",
                "gender": "girls",
                "category": "shoes",
                "data": "0x003326371d0121010001210200012a013f0200013f0122013f0200023f012a01000121022a02000122032a0120022b02000120032b"
            }
        ],
        [
            {
                "name": "11_white-slippers-w",
                "gender": "girls",
                "category": "shoes",
                "data": "0x003526371d01210222040002220145022b0200042b"
            }
        ],
        [
            {
                "name": "2_air-jordan-chicago-w",
                "gender": "girls",
                "category": "shoes",
                "data": "0x003226371d010001310400013102000133013101330200013301770200012501340125020001310125013201000135023202000225023201360231020001360331"
            }
        ],
        [
            {
                "name": "5_timberlands-w",
                "gender": "girls",
                "category": "shoes",
                "data": "0x003226371d0126012701260200022602000100012603000126012702000100012703000129022701000178027902000427027a012902000429"
            }
        ],
        [
            {
                "name": "7_flip-flops-w",
                "gender": "girls",
                "category": "shoes",
                "data": "0x003526371d01000121050001210100032002000420"
            }
        ],
        [
            {
                "name": "9_dress-shoes-w",
                "gender": "girls",
                "category": "shoes",
                "data": "0x003426371d01000124040001240200012401250124020003250100032502000425"
            }
        ],
        [
            {
                "name": "8_nike-cortez-w",
                "gender": "girls",
                "category": "shoes",
                "data": "0x003326371d012b0500012a0200017b012103000121014101220100017b022a0200024102220120022b02000120032b"
            }
        ],
        [
            {
                "name": "6_rebook-classic-w",
                "gender": "girls",
                "category": "shoes",
                "data": "0x003326371d0600012a02000137012201380200012a0137013801000122012a01220200042a032b0200042b"
            }
        ],
        [
            {
                "name": "15_open-toe-sandals-w",
                "gender": "girls",
                "category": "shoes",
                "data": "0x003426371d0100012c0300012c012d0200012d0100012d0400012c0100032c0200042c"
            }
        ],
        [
            {
                "name": "4-Winter-Gloves",
                "gender": "men",
                "category": "hands",
                "data": "0x00202723190116011c0a000116011c0116011c011d0a00011c011e011d0a00011d0100"
            }
        ],
        [
            {
                "name": "11-Kevlar-Gloves",
                "gender": "men",
                "category": "hands",
                "data": "0x001f2723190d00010d010e010d0a00010e010d010e020d0a00010d010e010d0a00010e0100"
            }
        ],
        [
            {
                "name": "0-Rubber-Gloves",
                "gender": "men",
                "category": "hands",
                "data": "0x001c272319010a01090a00010a0109010a01090a00010a0109010a01090a00010a0109010a01090a00010a0109010a01090a000209010a02090a000109010a01090a0001090100"
            }
        ],
        [
            {
                "name": "5-Nitrile-Gloves",
                "gender": "men",
                "category": "hands",
                "data": "0x0020272319010b010c0a00010b010c010b020c0a00010c010b010c0a00010b0100"
            }
        ],
        [
            {
                "name": "12-Surgical-Gloves",
                "gender": "men",
                "category": "hands",
                "data": "0x0020272319011a011b0a00011a011b011a021b0a00011b011a011b0a00011a0100"
            }
        ],
        [
            {
                "name": "3-MMA-Wraps",
                "gender": "men",
                "category": "hands",
                "data": "0x001f272319011f010f0a00011f010f02100a000210011f020f0800021f010f021f0a00021f"
            }
        ],
        [
            {
                "name": "1-Baseball-Gloves",
                "gender": "men",
                "category": "hands",
                "data": "0x00202926230100017c037d0100017c017d017c037d017d0118017d017c027d017c0118017c037d0200017d017c027d0200017c027d0100"
            }
        ],
        [
            {
                "name": "13-Fingerless-Gloves",
                "gender": "men",
                "category": "hands",
                "data": "0x001f2722190c000116011c0116011c0b00011c0116011c0b00011c"
            }
        ],
        [
            {
                "name": "10-Black-Gloves",
                "gender": "men",
                "category": "hands",
                "data": "0x0020272319011f01110a00011f0111011f02110a000111011f01110a00011f0100"
            }
        ],
        [
            {
                "name": "2-Boxing-Gloves",
                "gender": "men",
                "category": "hands",
                "data": "0x0020282518010002130a0002130100041508000415020f01150114080001140115020f0114011501140a000114011501140115011401150a00011501140115"
            }
        ],
        [
            {
                "name": "6-Studded-Leather-Gloves",
                "gender": "men",
                "category": "hands",
                "data": "0x001f272319011201110a0001120111011201110a00011201010112010101110a000111010101110a0001120101"
            }
        ],
        [
            {
                "name": "8-Leather-Gloves",
                "gender": "men",
                "category": "hands",
                "data": "0x001f2723190c00011f011c011f011c0a00021c011f021c0a00011c011f011c0a00011c0100"
            }
        ],
        [
            {
                "name": "9-White-Gloves",
                "gender": "men",
                "category": "hands",
                "data": "0x0020272319012001210a0001200121012002210a000121012001210a0001200100"
            }
        ],
        [
            {
                "name": "7-Combat-Gloves",
                "gender": "men",
                "category": "hands",
                "data": "0x001f2723190116011c0a000116011c011e011d0a00011e011d011e011d0b00011d021e0a00021e"
            }
        ],
        [
            {
                "name": "0-Pocket-Knife",
                "gender": "girls",
                "category": "weapons",
                "data": "0x00211b27160400013b0300013b01000200015b013b01000100025b0200025c0300015b0400"
            }
        ],
        [
            {
                "name": "8-Tire-Iron",
                "gender": "girls",
                "category": "weapons",
                "data": "0x00211b2d170300015d04000300015d0300015d0300015d0300015d0300015d0300015d0300015d0300015d0300015d035d0100"
            }
        ],
        [
            {
                "name": "11-Razor-Blade",
                "gender": "girls",
                "category": "weapons",
                "data": "0x00211b27190100011802000100015e015f015e015f015e015f015e"
            }
        ],
        [
            {
                "name": "5-AK47",
                "gender": "girls",
                "category": "weapons",
                "data": "0x001b1e30180100016002610200010001600261020001000160016103000100016001610300010001600400011f01120400011f011201610300011f01120400011f01120400011f02120300011f03120200011f0112010002120100011f0161020002120160016103000112016001610400016001610400011f01120400010001120400010001120400011f01120400010001120400"
            }
        ],
        [
            {
                "name": "6-Shovel",
                "gender": "girls",
                "category": "weapons",
                "data": "0x00211d3318010002600200010001600100016001000200016002000200016002000200016202000200016202000200016202000200016202000200016202000200016202000200016302000200016302000200016302000563056305630563010003630100"
            }
        ],
        [
            {
                "name": "1-Chain",
                "gender": "girls",
                "category": "weapons",
                "data": "0x00211b2e19010001640165010001650100026501000164016501640165010002650100016401650164016501000165016401000164"
            }
        ],
        [
            {
                "name": "3-Crowbar",
                "gender": "girls",
                "category": "weapons",
                "data": "0x00211b291802000116030002000116020001160200011602000116011601000116010001160100"
            }
        ],
        [
            {
                "name": "9-Police-Baton",
                "gender": "girls",
                "category": "weapons",
                "data": "0x00211b2c1802000166030002000166036602000166020001660200016602000166020001660200016602000166"
            }
        ],
        [
            {
                "name": "12-Chain",
                "gender": "girls",
                "category": "weapons",
                "data": "0x00211b2e19010001640165010001650100026501000164016501640165010002650100016401650164016501000165016401000164"
            }
        ],
        [
            {
                "name": "2-Knife",
                "gender": "girls",
                "category": "weapons",
                "data": "0x001a21221a0600015b0500025b0400035c0300035c01000200035b02000167035b030001000167015b04000168010001670400"
            }
        ],
        [
            {
                "name": "10-Pepper-Spray",
                "gender": "girls",
                "category": "weapons",
                "data": "0x00211c26160200021e0100011e02000169036a02000102030001000102010001020200010201000102010001020100"
            }
        ],
        [
            {
                "name": "17-Uzi",
                "gender": "girls",
                "category": "weapons",
                "data": "0x001f1e27160100021c05000100011c011605000100011c0216010003160100011c0116041c01000100011c0116011c04000100011c01160500011c02160500010001160600"
            }
        ],
        [
            {
                "name": "14-Brass-Knuckles",
                "gender": "girls",
                "category": "weapons",
                "data": "0x00201d24190200013b01000100013b0100013b013b0100013b01000100013b0200"
            }
        ],
        [
            {
                "name": "4-Handgun",
                "gender": "girls",
                "category": "weapons",
                "data": "0x00211b28180100023e0151013e01000251010001510200015102000151020001510200"
            }
        ],
        [
            {
                "name": "7-Baseball-Bat",
                "gender": "girls",
                "category": "weapons",
                "data": "0x00211b3319010001160200010001160100011601000116010001160100016b0162016b0162016b0162016b0162016b0162016b0162016b0162016b0162016b0162016b0162016b0262"
            }
        ],
        [
            {
                "name": "15-Shotgun",
                "gender": "girls",
                "category": "weapons",
                "data": "0x00211c30180100013b0100013b033b0100023b0200013b011c0200013b011c0200013b011c0200013b011c0200013b011c0200013b011c0200013b011c0200013b011c0200013b011c0200013b011c0200013b011c0200013b0300"
            }
        ],
        [
            {
                "name": "13-Taser",
                "gender": "girls",
                "category": "weapons",
                "data": "0x00201c26180100013b0100013b033b0100023b0200013b011c0200013b011c0200016c016d0200"
            }
        ],
        [
            {
                "name": "16-Glock",
                "gender": "girls",
                "category": "weapons",
                "data": "0x00201c2518010001160200021601000116010002160100010001160200010001160200"
            }
        ],
        [
            {
                "name": "man",
                "gender": "men",
                "category": "silhouette",
                "data": "0x000927361907000363040006000563030006000563030006000563030006000563030007000463030007000363040007000263050004000763030002000b63010001000d6301000d6301000d630e630e63026301000b63026301000b63026301000b63026301000b63026301000b63026301000b63026301000b63026301000b63026301000b630c630100016302630100036303000463010003000363030003630200030003630300036302000300036303000363020003000363030003630200030003630300036302000300036303000363020003000363030003630200030003630300036302000300026304000263030003000263040002630300030002630400026303000300026304000263030003000263040002630300030002630400026303000300026304000263030003000263040002630300030002630400026303000300026304000363020003000363030004630100"
            }
        ],
        [
            {
                "name": "1-Silver-Chain",
                "gender": "men",
                "category": "neck",
                "data": "0x001124141f010104000100010102000101020002010100"
            }
        ],
        [
            {
                "name": "0-Bronze-Chain",
                "gender": "men",
                "category": "neck",
                "data": "0x001124141f010804000100010802000108020002080100"
            }
        ],
        [
            {
                "name": "2-Gold-Chain",
                "gender": "men",
                "category": "neck",
                "data": "0x001124141f010304000100010302000103020002030100"
            }
        ],
        [
            {
                "name": "lady",
                "gender": "girls",
                "category": "silhouette",
                "data": "0x000a26361a050004630300040006630200040007630100020009630100020008630200020002630100056302000300016301000563020006000363030006000263040006000263040004000663020003000863010002000a6302000a63010002630100086301000163020006630100016301000163030005630100016301000163030004630200016301000163030004630200016301000163030004630200016301000163030004630200016301000163020006630100016302630100096302630100076301000163016302000863010004000263020002630200040002630200026302000400026302000263020004000263020002630200040002630200026302000400026302000263020004000263020002630200040002630200026302000400016303000163030004000163030001630300040001630300016303000400016303000163030004000163030001630300040001630300016303000400016303000163030004000163030001630300040001630300016303000400016303000163030004000263020003630100"
            }
        ]
    ]
}